Workbook

Sheet Summary
A1: Celsius Holdings (CELH) — Valuation Summary
A2: Personal equity research project — DCF + comparable companies. $ per share unless noted.
A4: Recommendation | B4: HOLD
A6: Valuation method | B6: Value / share
A7: DCF — base case | B7: =DCF!B26 -> 26.228994 | D7: WACC 9.5%, term. g 3.0%
A8: DCF — bull case | B8: =DCF!G33 -> 37.519319 | D8: WACC 8.5%, term. g 4.0%
A9: DCF — bear case | B9: =DCF!C37 -> 20.233766 | D9: WACC 10.5%, term. g 2.0%
A10: Comps — EV/EBITDA | B10: =Comps!B19 -> 39.208731 | D10: peer median EV/EBITDA
A11: Comps — P/E | B11: =Comps!B20 -> 25.728 | D11: peer median P/E
A12: Blended target | B12: =AVERAGE(B7,B10,B11) -> 30.388575 | D12: avg of base DCF + comps
A13: Current price | B13: =Inputs!B5 -> 30.8
A14: Upside / (downside) | B14: =B12/B13-1 -> -0.013357951
A17: Implied value by method ($/share)

Sheet Inputs
A1: Celsius Holdings (CELH) — Model Inputs
A2: $ in millions, except per-share data
A4: Market data
A5: Current share price | B5: 30.8 | C5: Source: Yahoo Finance, CELH, Jun 2026
A6: Diluted shares outstanding (mm) | B6: 255.64 | C6: Market cap / price (~$7.7B / $30.50)
A7: Market capitalization | B7: =B5*B6 -> 7873.712
A8: Total debt | B8: 675.88 | C8: Term Loan B for Alani Nu acquisition (~$900mm)
A9: Cash & equivalents | B9: 549.2 | C9: Source: Celsius FY2025 results
A10: Net debt | B10: =B8-B9 -> 126.68
A11: Enterprise value | B11: =B7+B10 -> 8000.392
A13: Financials
A14: FY2025 revenue | B14: 2515 | C14: Source: Celsius FY2025 results (record $2.5B)
A15: TTM revenue | B15: 2969 | C15: Source: Yahoo Finance, TTM Jun 2026
A16: FY2025 EBIT | B16: 174.01 | C16: Source: Macrotrends, FY2025 EBIT
A17: Adj. EBITDA (TTM, est.) | B17: 500 | C17: Approx adjusted EBITDA; refresh from filings
A18: Adj. diluted EPS (TTM) | B18: 1.34 | C18: Source: Celsius FY2025 non-GAAP adj. EPS
A20: DCF assumptions
A21: Tax rate | B21: 0.25 | C21: Assumption (statutory ~21% + state)
A22: WACC | B22: 0.095 | C22: Assumption (beverage growth co.)
A23: Terminal growth rate | B23: 0.03 | C23: Assumption (long-run, ~GDP+)
A24: D&A (% of revenue) | B24: 0.03 | C24: Assumption
A25: Capex (% of revenue) | B25: 0.03 | C25: Assumption
A26: Δ NWC (% of Δ revenue) | B26: 0.05 | C26: Assumption

Sheet DCF
A1: Celsius Holdings (CELH) — Discounted Cash Flow
A2: $ in millions, except per-share data
B4: FY2025A | C4: FY2026E | D4: FY2027E | E4: FY2028E | F4: FY2029E | G4: FY2030E
A5: Revenue growth % | C5: 0.18 | D5: 0.14 | E5: 0.11 | F5: 0.08 | G5: 0.06
A6: Revenue | B6: =Inputs!B14 -> 2515 | C6: =B6*(1+C5) -> 2967.7 | D6: =C6*(1+D5) -> 3383.178 | E6: =D6*(1+E5) -> 3755.3276 | F6: =E6*(1+F5) -> 4055.7538 | G6: =F6*(1+G5) -> 4299.099
A7: EBIT margin % | C7: 0.11 | D7: 0.13 | E7: 0.15 | F7: 0.16 | G7: 0.17
A8: EBIT | B8: =Inputs!B16 -> 174.01 | C8: =C6*C7 -> 326.447 | D8: =D6*D7 -> 439.81314 | E8: =E6*E7 -> 563.29914 | F8: =F6*F7 -> 648.92061 | G8: =G6*G7 -> 730.84683
A9: Tax rate % | C9: =Inputs!$B$21 -> 0.25 | D9: =Inputs!$B$21 -> 0.25 | E9: =Inputs!$B$21 -> 0.25 | F9: =Inputs!$B$21 -> 0.25 | G9: =Inputs!$B$21 -> 0.25
A10: NOPAT | C10: =C8*(1-C9) -> 244.83525 | D10: =D8*(1-D9) -> 329.85986 | E10: =E8*(1-E9) -> 422.47435 | F10: =F8*(1-F9) -> 486.69045 | G10: =G8*(1-G9) -> 548.13512
A11: (+) D&A | C11: =C6*Inputs!$B$24 -> 89.031 | D11: =D6*Inputs!$B$24 -> 101.49534 | E11: =E6*Inputs!$B$24 -> 112.65983 | F11: =F6*Inputs!$B$24 -> 121.67261 | G11: =G6*Inputs!$B$24 -> 128.97297
A12: (-) Capex | C12: =-C6*Inputs!$B$25 -> -89.031 | D12: =-D6*Inputs!$B$25 -> -101.49534 | E12: =-E6*Inputs!$B$25 -> -112.65983 | F12: =-F6*Inputs!$B$25 -> -121.67261 | G12: =-G6*Inputs!$B$25 -> -128.97297
A13: (-) Δ NWC | C13: =-(C6-B6)*Inputs!$B$26 -> -22.635 | D13: =-(D6-C6)*Inputs!$B$26 -> -20.7739 | E13: =-(E6-D6)*Inputs!$B$26 -> -18.607479 | F13: =-(F6-E6)*Inputs!$B$26 -> -15.02131 | G13: =-(G6-F6)*Inputs!$B$26 -> -12.167261
A14: Unlevered FCF | C14: =C10+C11+C12+C13 -> 222.20025 | D14: =D10+D11+D12+D13 -> 309.08596 | E14: =E10+E11+E12+E13 -> 403.86687 | F14: =F10+F11+F12+F13 -> 471.66914 | G14: =G10+G11+G12+G13 -> 535.96786
A15: Discount period | C15: 1 | D15: 2 | E15: 3 | F15: 4 | G15: 5
A16: Discount factor | C16: =1/(1+Inputs!$B$22)^C15 -> 0.91324201 | D16: =1/(1+Inputs!$B$22)^D15 -> 0.83401097 | E16: =1/(1+Inputs!$B$22)^E15 -> 0.76165385 | F16: =1/(1+Inputs!$B$22)^F15 -> 0.69557429 | G16: =1/(1+Inputs!$B$22)^G15 -> 0.63522767
A17: PV of FCF | C17: =C14*C16 -> 202.9226 | D17: =D14*D16 -> 257.78108 | E17: =E14*E16 -> 307.60676 | F17: =F14*F16 -> 328.08093 | G17: =G14*G16 -> 340.46161
A19: Sum PV of explicit FCF | B19: =SUM(C17:G17) -> 1436.853
A20: Terminal value (FY2030) | B20: =G14*(1+Inputs!B23)/(Inputs!B22-Inputs!B23) -> 8493.0292
A21: PV of terminal value | B21: =B20*G16 -> 5395.0071
A22: Enterprise value | B22: =B19+B21 -> 6831.8601
A23: (-) Net debt | B23: =-Inputs!B10 -> -126.68
A24: Equity value | B24: =B22+B23 -> 6705.1801
A25: Diluted shares (mm) | B25: =Inputs!B6 -> 255.64
A26: Intrinsic value / share | B26: =B24/B25 -> 26.228994
A27: Current price | B27: =Inputs!B5 -> 30.8
A28: Upside / (downside) | B28: =B26/B27-1 -> -0.14840928
A31: Sensitivity — intrinsic value / share
A32: WACC ↓ / term. growth → | C32: 0.02 | D32: 0.025 | E32: 0.03 | F32: 0.035 | G32: 0.04
B33: 0.085 | C33: =(SUMPRODUCT($C$14:$G$14,1/(1+$B33)^$C$15:$G$15)+($G$14*(1+C$32)/($B33-C$32))/((1+$B33)^$G$15)-Inputs!$B$10)/Inputs!$B$6 -> 27.175162 | D33: =(SUMPRODUCT($C$14:$G$14,1/(1+$B33)^$C$15:$G$15)+($G$14*(1+D$32)/($B33-D$32))/((1+$B33)^$G$15)-Inputs!$B$10)/Inputs!$B$6 -> 29.114691 | E33: =(SUMPRODUCT($C$14:$G$14,1/(1+$B33)^$C$15:$G$15)+($G$14*(1+E$32)/($B33-E$32))/((1+$B33)^$G$15)-Inputs!$B$10)/Inputs!$B$6 -> 31.406862 | F33: =(SUMPRODUCT($C$14:$G$14,1/(1+$B33)^$C$15:$G$15)+($G$14*(1+F$32)/($B33-F$32))/((1+$B33)^$G$15)-Inputs!$B$10)/Inputs!$B$6 -> 34.157468 | G33: =(SUMPRODUCT($C$14:$G$14,1/(1+$B33)^$C$15:$G$15)+($G$14*(1+G$32)/($B33-G$32))/((1+$B33)^$G$15)-Inputs!$B$10)/Inputs!$B$6 -> 37.519319
B34: 0.09 | C34: =(SUMPRODUCT($C$14:$G$14,1/(1+$B34)^$C$15:$G$15)+($G$14*(1+C$32)/($B34-C$32))/((1+$B34)^$G$15)-Inputs!$B$10)/Inputs!$B$6 -> 25.0646 | D34: =(SUMPRODUCT($C$14:$G$14,1/(1+$B34)^$C$15:$G$15)+($G$14*(1+D$32)/($B34-D$32))/((1+$B34)^$G$15)-Inputs!$B$10)/Inputs!$B$6 -> 26.696759 | E34: =(SUMPRODUCT($C$14:$G$14,1/(1+$B34)^$C$15:$G$15)+($G$14*(1+E$32)/($B34-E$32))/((1+$B34)^$G$15)-Inputs!$B$10)/Inputs!$B$6 -> 28.600945 | F34: =(SUMPRODUCT($C$14:$G$14,1/(1+$B34)^$C$15:$G$15)+($G$14*(1+F$32)/($B34-F$32))/((1+$B34)^$G$15)-Inputs!$B$10)/Inputs!$B$6 -> 30.851347 | G34: =(SUMPRODUCT($C$14:$G$14,1/(1+$B34)^$C$15:$G$15)+($G$14*(1+G$32)/($B34-G$32))/((1+$B34)^$G$15)-Inputs!$B$10)/Inputs!$B$6 -> 33.551829
B35: 0.095 | C35: =(SUMPRODUCT($C$14:$G$14,1/(1+$B35)^$C$15:$G$15)+($G$14*(1+C$32)/($B35-C$32))/((1+$B35)^$G$15)-Inputs!$B$10)/Inputs!$B$6 -> 23.237564 | D35: =(SUMPRODUCT($C$14:$G$14,1/(1+$B35)^$C$15:$G$15)+($G$14*(1+D$32)/($B35-D$32))/((1+$B35)^$G$15)-Inputs!$B$10)/Inputs!$B$6 -> 24.626443 | E35: =(SUMPRODUCT($C$14:$G$14,1/(1+$B35)^$C$15:$G$15)+($G$14*(1+E$32)/($B35-E$32))/((1+$B35)^$G$15)-Inputs!$B$10)/Inputs!$B$6 -> 26.228994 | F35: =(SUMPRODUCT($C$14:$G$14,1/(1+$B35)^$C$15:$G$15)+($G$14*(1+F$32)/($B35-F$32))/((1+$B35)^$G$15)-Inputs!$B$10)/Inputs!$B$6 -> 28.098638 | G35: =(SUMPRODUCT($C$14:$G$14,1/(1+$B35)^$C$15:$G$15)+($G$14*(1+G$32)/($B35-G$32))/((1+$B35)^$G$15)-Inputs!$B$10)/Inputs!$B$6 -> 30.308217
B36: 0.1 | C36: =(SUMPRODUCT($C$14:$G$14,1/(1+$B36)^$C$15:$G$15)+($G$14*(1+C$32)/($B36-C$32))/((1+$B36)^$G$15)-Inputs!$B$10)/Inputs!$B$6 -> 21.640848 | D36: =(SUMPRODUCT($C$14:$G$14,1/(1+$B36)^$C$15:$G$15)+($G$14*(1+D$32)/($B36-D$32))/((1+$B36)^$G$15)-Inputs!$B$10)/Inputs!$B$6 -> 22.834171 | E36: =(SUMPRODUCT($C$14:$G$14,1/(1+$B36)^$C$15:$G$15)+($G$14*(1+E$32)/($B36-E$32))/((1+$B36)^$G$15)-Inputs!$B$10)/Inputs!$B$6 -> 24.197969 | F36: =(SUMPRODUCT($C$14:$G$14,1/(1+$B36)^$C$15:$G$15)+($G$14*(1+F$32)/($B36-F$32))/((1+$B36)^$G$15)-Inputs!$B$10)/Inputs!$B$6 -> 25.771581 | G36: =(SUMPRODUCT($C$14:$G$14,1/(1+$B36)^$C$15:$G$15)+($G$14*(1+G$32)/($B36-G$32))/((1+$B36)^$G$15)-Inputs!$B$10)/Inputs!$B$6 -> 27.607463
B37: 0.105 | C37: =(SUMPRODUCT($C$14:$G$14,1/(1+$B37)^$C$15:$G$15)+($G$14*(1+C$32)/($B37-C$32))/((1+$B37)^$G$15)-Inputs!$B$10)/Inputs!$B$6 -> 20.233766 | D37: =(SUMPRODUCT($C$14:$G$14,1/(1+$B37)^$C$15:$G$15)+($G$14*(1+D$32)/($B37-D$32))/((1+$B37)^$G$15)-Inputs!$B$10)/Inputs!$B$6 -> 21.26777 | E37: =(SUMPRODUCT($C$14:$G$14,1/(1+$B37)^$C$15:$G$15)+($G$14*(1+E$32)/($B37-E$32))/((1+$B37)^$G$15)-Inputs!$B$10)/Inputs!$B$6 -> 22.43964 | F37: =(SUMPRODUCT($C$14:$G$14,1/(1+$B37)^$C$15:$G$15)+($G$14*(1+F$32)/($B37-F$32))/((1+$B37)^$G$15)-Inputs!$B$10)/Inputs!$B$6 -> 23.77892 | G37: =(SUMPRODUCT($C$14:$G$14,1/(1+$B37)^$C$15:$G$15)+($G$14*(1+G$32)/($B37-G$32))/((1+$B37)^$G$15)-Inputs!$B$10)/Inputs!$B$6 -> 25.324244

Sheet Comps
A1: Celsius Holdings (CELH) — Comparable Companies
A2: Peer multiples are approximate (Jun 2026); refresh before use.
A4: Company | B4: Ticker | C4: EV/Revenue | D4: EV/EBITDA | E4: P/E
A5: Monster Beverage | B5: MNST | C5: 10 | D5: 31.2 | E5: 35.3
A6: Keurig Dr Pepper | B6: KDP | C6: 4.7 | D6: 18 | E6: 12.2
A7: Coca-Cola | B7: KO | C7: 7.7 | D7: 22.6 | E7: 22.8
A8: PepsiCo | B8: PEP | C8: 2.5 | D8: 12.9 | E8: 15.6
A9: Median | C9: =MEDIAN(C5:C8) -> 6.2 | D9: =MEDIAN(D5:D8) -> 20.3 | E9: =MEDIAN(E5:E8) -> 19.2
A11: Implied valuation for CELH
A12: CELH TTM revenue | B12: =Inputs!B15 -> 2969
A13: CELH adj. EBITDA | B13: =Inputs!B17 -> 500
A14: CELH adj. EPS | B14: =Inputs!B18 -> 1.34
A15: Net debt | B15: =Inputs!B10 -> 126.68
A16: Shares (mm) | B16: =Inputs!B6 -> 255.64
A18: Implied price — EV/Revenue (n.m.) | B18: =(C9*B12-B15)/B16 -> 71.511188 | D18: Excluded: CELH margins << peers, so revenue multiple overstates value
A19: Implied price — EV/EBITDA | B19: =(D9*B13-B15)/B16 -> 39.208731
A20: Implied price — P/E | B20: =E9*B14 -> 25.728
A21: Average implied (EBITDA + P/E) | B21: =AVERAGE(B19:B20) -> 32.468366
